Metadata-Version: 2.1
Name: physicalquantity
Version: 0.1.1
Summary: Simple library for working with physical quantities
Home-page: https://github.com/pibara/physicalquantity
Author: Rob J Meijer
Author-email: pibara@gmail.com
License: BSD
Keywords: units quantities
Classifier: Development Status :: 4 - Beta
Classifier: Intended Audience :: Developers
Classifier: Topic :: Software Development :: Libraries
Classifier: License :: OSI Approved :: BSD License
Classifier: Programming Language :: Python :: 3
Classifier: Operating System :: OS Independent
Classifier: Environment :: Other Environment
License-File: LICENSE.txt
Requires-Dist: python-dateutil
Requires-Dist: pytz
Requires-Dist: simplejson
